blspy.cpython-312-darwin.so
pshenmic_blspy-1.3.1.dev2.dist-info/LICENSE
pshenmic_blspy-1.3.1.dev2.dist-info/METADATA
pshenmic_blspy-1.3.1.dev2.dist-info/WHEEL
pshenmic_blspy-1.3.1.dev2.dist-info/top_level.txt
pshenmic_blspy-1.3.1.dev2.dist-info/RECORD
