Metadata-Version: 2.1
Name: pshenmic_blspy
Version: 1.3.1.dev2
Summary: BLS signatures in c++ (python bindings)
Home-page: https://github.com/pshenmic/bls-signatures
Author: Mariano Sorgente
Author-email: mariano@chia.net
Requires-Python: >=3.7
License-File: LICENSE
Requires-Dist: wheel
